learninghouse/__init__.py
learninghouse/__main__.py
learninghouse/_version.py
learninghouse/service.py
learninghouse/api/__init__.py
learninghouse/api/auth.py
learninghouse/api/brain.py
learninghouse/api/docs.py
learninghouse/api/middleware.py
learninghouse/api/sensor.py
learninghouse/api/ui.py
learninghouse/api/errors/__init__.py
learninghouse/api/errors/auth.py
learninghouse/api/errors/brain.py
learninghouse/api/errors/sensor.py
learninghouse/core/__init__.py
learninghouse/core/logger/__init__.py
learninghouse/core/logger/models.py
learninghouse/core/settings/__init__.py
learninghouse/core/settings/models.py
learninghouse/models/__init__.py
learninghouse/models/auth.py
learninghouse/models/base.py
learninghouse/models/brain.py
learninghouse/models/preprocessing.py
learninghouse/models/sensor.py
learninghouse/services/__init__.py
learninghouse/services/auth.py
learninghouse/services/brain.py
learninghouse/services/preprocessing.py
learninghouse/services/sensor.py
learninghouse/static/favicon.ico
learninghouse/static/docs/swagger-ui-bundle.js
learninghouse/static/docs/swagger-ui-bundle.js.map
learninghouse/static/docs/swagger-ui.css
learninghouse/static/docs/swagger-ui.css.map
learninghouse/ui/12.f51d61a602bd44f8.js
learninghouse/ui/247.f1ef928f3ffd3d14.js
learninghouse/ui/3rdpartylicenses.txt
learninghouse/ui/766.fbfc5c5b7b050675.js
learninghouse/ui/common.ebb0c9901a929b96.js
learninghouse/ui/favicon.ico
learninghouse/ui/index.html
learninghouse/ui/main.7af81aa7b997ef87.js
learninghouse/ui/material-icons.3705a31196184f2e.woff2
learninghouse/ui/polyfills.fb9dd10c5e35e33e.js
learninghouse/ui/roboto-v30-latin-300.006981bf6ff6087f.woff
learninghouse/ui/roboto-v30-latin-300.a4eae32d320f45e6.woff2
learninghouse/ui/roboto-v30-latin-300italic.43a343143e72a1ca.woff2
learninghouse/ui/roboto-v30-latin-300italic.9d3ffcc3b116eed0.woff
learninghouse/ui/roboto-v30-latin-500.3170fd9aa9258fe0.woff2
learninghouse/ui/roboto-v30-latin-500.e5748c3b7acf0d45.woff
learninghouse-1.10.2.dist-info/LICENSE
learninghouse-1.10.2.dist-info/METADATA
learninghouse-1.10.2.dist-info/WHEEL
learninghouse-1.10.2.dist-info/entry_points.txt
learninghouse-1.10.2.dist-info/top_level.txt
learninghouse-1.10.2.dist-info/RECORD
