Metadata-Version: 2.1
Name: learninghouse
Version: 1.10.2
Summary: learningHouse - Teach your smart home everything
Home-page: https://github.com/LearningHouseService/learninghouse-monorepo
Author: Johannes Ott
Author-email: info@johannes-ott.net
Project-URL: Bug Reports, https://github.com/LearningHouseService/learninghouse/issues
Keywords: smart home,machine learning,house automation
Classifier: Development Status :: 5 - Production/Stable
Classifier: Topic :: Home Automation
Classifier: License :: OSI Approved :: MIT License
Classifier: Framework :: FastAPI
Classifier: Natural Language :: English
Classifier: Programming Language :: Python :: 3 :: Only
Classifier: Programming Language :: Python :: 3.10
Requires-Python: >=3.10, <4
License-File: LICENSE
Requires-Dist: fastapi ==0.112.0
Requires-Dist: loguru ==0.7.2
Requires-Dist: numpy ==2.0.1
Requires-Dist: pandas ==2.2.2
Requires-Dist: passlib ==1.7.4
Requires-Dist: pydantic ==2.8.2
Requires-Dist: PyJWT ==2.8.0
Requires-Dist: scikit-learn ==1.5.1
Requires-Dist: uvicorn[standard] ==0.30.5
